mlt/__init__.py
mlt/_version.py
mlt/event_handler.py
mlt/main.py
mlt/commands/__init__.py
mlt/commands/base.py
mlt/commands/build.py
mlt/commands/config.py
mlt/commands/deploy.py
mlt/commands/events.py
mlt/commands/init.py
mlt/commands/logs.py
mlt/commands/status.py
mlt/commands/sync.py
mlt/commands/templates.py
mlt/commands/undeploy.py
mlt/commands/update_template.py
mlt/utils/__init__.py
mlt/utils/build_helpers.py
mlt/utils/config_helpers.py
mlt/utils/constants.py
mlt/utils/files.py
mlt/utils/git_helpers.py
mlt/utils/kubernetes_debug_wrapper.py
mlt/utils/kubernetes_helpers.py
mlt/utils/localhost_helpers.py
mlt/utils/log_helpers.py
mlt/utils/process_helpers.py
mlt/utils/progress_bar.py
mlt/utils/regex_checks.py
mlt/utils/schema.py
mlt/utils/sync_helpers.py
mlt-0.3.0.dist-info/LICENSE.txt
mlt-0.3.0.dist-info/METADATA
mlt-0.3.0.dist-info/RECORD
mlt-0.3.0.dist-info/WHEEL
mlt-0.3.0.dist-info/entry_points.txt
mlt-0.3.0.dist-info/top_level.txt
mlt-templates/__init__.py
mlt-templates/experiments/.gitignore
mlt-templates/experiments/Dockerfile
mlt-templates/experiments/EXPERIMENTS_VERSION.txt
mlt-templates/experiments/Makefile
mlt-templates/experiments/README.md
mlt-templates/experiments/crd-requirements.txt
mlt-templates/experiments/experiment_status.sh
mlt-templates/experiments/requirements.txt
mlt-templates/experiments/k8s/.gitignore
mlt-templates/experiments/k8s/.gitignore-e
mlt-templates/experiments/k8s-templates/experiment.yaml
mlt-templates/experiments/k8s-templates/optimizer.yaml
mlt-templates/hello-world/.gitignore
mlt-templates/hello-world/Dockerfile
mlt-templates/hello-world/Makefile
mlt-templates/hello-world/README.md
mlt-templates/hello-world/main.py
mlt-templates/hello-world/parameters.json
mlt-templates/hello-world/requirements.txt
mlt-templates/hello-world/k8s/.gitignore
mlt-templates/hello-world/k8s/.gitignore-e
mlt-templates/hello-world/k8s-templates/job.yaml
mlt-templates/horovod/.gitignore
mlt-templates/horovod/Dockerfile.cpu
mlt-templates/horovod/Dockerfile.gpu
mlt-templates/horovod/LICENSE
mlt-templates/horovod/Makefile
mlt-templates/horovod/README.md
