Metadata-Version: 2.1
Name: mlt
Version: 0.3.0
Summary: Machine Learning Container Templates
Home-page: https://github.com/IntelAI/mlt
Author: Intel Nervana
Author-email: intelnervana@intel.com
License: UNKNOWN
Platform: UNKNOWN
Classifier: Development Status :: 3 - Alpha
Classifier: Environment :: Console
Classifier: Intended Audience :: End Users/Desktop
Classifier: Intended Audience :: Developers
Classifier: Intended Audience :: Science/Research
Classifier: Operating System :: POSIX
Classifier: Operating System :: MacOS :: MacOS X
Classifier: Programming Language :: Python :: 3
Classifier: Topic :: Scientific/Engineering :: Artificial Intelligence
Classifier: Topic :: Scientific/Engineering :: Information Analysis
Classifier: Topic :: System :: Distributed Computing
Requires-Dist: pip (>=10.0.1)
Requires-Dist: conditional (>=1.2)
Requires-Dist: docopt (>=0.6.2)
Requires-Dist: progressbar2 (>=3.36.0)
Requires-Dist: tabulate (>=0.8.2)
Requires-Dist: termcolor (>=1.1.0)
Requires-Dist: PyYAML (>=3.12)
Requires-Dist: watchdog (>=0.8.3)
Requires-Dist: jsonschema (==2.6.0)
Requires-Dist: pytz (==2018.5)
